MANIFEST.in
README.rst
setup.cfg
setup.py
hghudson/__init__.py
hghudson.egg-info/PKG-INFO
hghudson.egg-info/SOURCES.txt
hghudson.egg-info/dependency_links.txt
hghudson.egg-info/entry_points.txt
hghudson.egg-info/top_level.txt
hghudson.egg-info/zip-safe
hghudson/tests/__init__.py
hghudson/tests/testhook.py