Metadata-Version: 1.0
Name: hghudson
Version: 0.1.1dev
Summary: Mercurial integration with Hudson
Home-page: http://www.gitorious.org/hghudson
Author: Néstor Salceda
Author-email: nestor.salceda@gmail.com
License: MIT/X11
Platform: UNKNOWN
Classifier: Development Status :: 4 - Beta
Classifier: Intended Audience :: Developers
Classifier: Intended Audience :: System Administrators
Classifier: License :: OSI Approved :: MIT License
Classifier: Programming Language :: Python :: 2.6
Classifier: Topic :: Software Development :: Quality Assurance
Classifier: Topic :: Software Development :: Version Control
